jet/__init__.py
jet/exceptions.py
jet/jes.py
jet/jet.py
jet/utils.py
json_encrypted_token-0.0.6.dist-info/LICENSE
json_encrypted_token-0.0.6.dist-info/METADATA
json_encrypted_token-0.0.6.dist-info/WHEEL
json_encrypted_token-0.0.6.dist-info/top_level.txt
json_encrypted_token-0.0.6.dist-info/RECORD
