Metadata-Version: 2.1
Name: json-encrypted-token
Version: 0.0.6
Summary: JET - JSON Encrypted Token
Home-page: https://github.com/FR98/jet-python
Author: Francisco Rosal
Author-email: frangrosalo@hotmail.com
License: UNKNOWN
Platform: UNKNOWN
Classifier: Programming Language :: Python :: 3
Classifier: License :: OSI Approved :: MIT License
Classifier: Operating System :: OS Independent
Requires-Python: >=3.6
Requires-Dist: backports.pbkdf2 (==0.1)
Requires-Dist: cffi (==1.14.3)
Requires-Dist: cryptography (==3.1.1)
Requires-Dist: pycparser (==2.20)
Requires-Dist: six (==1.15.0)
